{
  "updated_at": "Mon Jan 26 08:07:29 2026",
  "stats": [
    {
      "model_name": "MacBook Air 13 (2020, M1)",
      "processor": "Apple M1",
      "ram": 8,
      "ssd": 256,
      "min_price": 32000,
      "max_price": 36000,
      "median_price": 34695,
      "buyout_price": 20000,
      "samples_count": 100,
      "updated_at": "Sun Jan 25 22:11:52 2026"
    },
    {
      "model_name": "MacBook Air 13 (2020, M1)",
      "processor": "Apple M1",
      "ram": 16,
      "ssd": 256,
      "min_price": 40990,
      "max_price": 50000,
      "median_price": 45000,
      "buyout_price": 28000,
      "samples_count": 141,
      "updated_at": "Sun Jan 25 22:12:09 2026"
    },
    {
      "model_name": "MacBook Air 13 (2020, M1)",
      "processor": "Apple M1",
      "ram": 8,
      "ssd": 512,
      "min_price": 37000,
      "max_price": 45000,
      "median_price": 40500,
      "buyout_price": 25000,
      "samples_count": 62,
      "updated_at": "Sun Jan 25 22:12:27 2026"
    },
    {
      "model_name": "MacBook Air 13 (2020, M1)",
      "processor": "Apple M1",
      "ram": 16,
      "ssd": 512,
      "min_price": 47900,
      "max_price": 60490,
      "median_price": 54900,
      "buyout_price": 35000,
      "samples_count": 84,
      "updated_at": "Sun Jan 25 22:12:44 2026"
    },
    {
      "model_name": "MacBook Air 13 (2020, M1)",
      "processor": "Apple M1",
      "ram": 16,
      "ssd": 1024,
      "min_price": 51999,
      "max_price": 70490,
      "median_price": 65000,
      "buyout_price": 39000,
      "samples_count": 34,
      "updated_at": "Sun Jan 25 22:13:04 2026"
    },
    {
      "model_name": "MacBook Air 13 (2022, M2)",
      "processor": "Apple M2",
      "ram": 8,
      "ssd": 256,
      "min_price": 49999,
      "max_price": 58990,
      "median_price": 54575,
      "buyout_price": 37000,
      "samples_count": 97,
      "updated_at": "Sun Jan 25 22:13:18 2026"
    },
    {
      "model_name": "MacBook Air 13 (2022, M2)",
      "processor": "Apple M2",
      "ram": 16,
      "ssd": 256,
      "min_price": 58500,
      "max_price": 64500,
      "median_price": 61900,
      "buyout_price": 46000,
      "samples_count": 84,
      "updated_at": "Sun Jan 25 22:13:32 2026"
    },
    {
      "model_name": "MacBook Air 13 (2022, M2)",
      "processor": "Apple M2",
      "ram": 8,
      "ssd": 512,
      "min_price": 50000,
      "max_price": 64999,
      "median_price": 55000,
      "buyout_price": 38000,
      "samples_count": 91,
      "updated_at": "Sun Jan 25 22:13:49 2026"
    },
    {
      "model_name": "MacBook Air 13 (2022, M2)",
      "processor": "Apple M2",
      "ram": 16,
      "ssd": 512,
      "min_price": 73590,
      "max_price": 158900,
      "median_price": 81990,
      "buyout_price": 61000,
      "samples_count": 64,
      "updated_at": "Sun Jan 25 22:14:05 2026"
    },
    {
      "model_name": "MacBook Air 13 (2024, M3)",
      "processor": "Apple M3",
      "ram": 8,
      "ssd": 256,
      "min_price": 59990,
      "max_price": 73000,
      "median_price": 62900,
      "buyout_price": 47000,
      "samples_count": 115,
      "updated_at": "Sun Jan 25 22:14:19 2026"
    },
    {
      "model_name": "MacBook Air 13 (2024, M3)",
      "processor": "Apple M3",
      "ram": 16,
      "ssd": 256,
      "min_price": 75800,
      "max_price": 79787,
      "median_price": 77590,
      "buyout_price": 63000,
      "samples_count": 50,
      "updated_at": "Sun Jan 25 22:14:37 2026"
    },
    {
      "model_name": "MacBook Air 13 (2024, M3)",
      "processor": "Apple M3",
      "ram": 8,
      "ssd": 512,
      "min_price": 71990,
      "max_price": 84990,
      "median_price": 79495,
      "buyout_price": 59000,
      "samples_count": 135,
      "updated_at": "Sun Jan 25 22:14:55 2026"
    },
    {
      "model_name": "MacBook Air 13 (2024, M3)",
      "processor": "Apple M3",
      "ram": 16,
      "ssd": 512,
      "min_price": 80000,
      "max_price": 94080,
      "median_price": 89990,
      "buyout_price": 68000,
      "samples_count": 144,
      "updated_at": "Sun Jan 25 18:37:03 2026"
    },
    {
      "model_name": "MacBook Air 13 (2024, M3)",
      "processor": "Apple M3",
      "ram": 24,
      "ssd": 512,
      "min_price": 104990,
      "max_price": 116990,
      "median_price": 109990,
      "buyout_price": 92000,
      "samples_count": 50,
      "updated_at": "Sun Jan 25 22:15:48 2026"
    },
    {
      "model_name": "MacBook Air 13 (2025, M4)",
      "processor": "Apple M4",
      "ram": 16,
      "ssd": 256,
      "min_price": 69000,
      "max_price": 70500,
      "median_price": 69999,
      "buyout_price": 57000,
      "samples_count": 99,
      "updated_at": "Sun Jan 25 22:16:02 2026"
    },
    {
      "model_name": "MacBook Air 13 (2025, M4)",
      "processor": "Apple M4",
      "ram": 16,
      "ssd": 512,
      "min_price": 85000,
      "max_price": 86590,
      "median_price": 85990,
      "buyout_price": 73000,
      "samples_count": 50,
      "updated_at": "Sun Jan 25 22:16:19 2026"
    },
    {
      "model_name": "MacBook Air 13 (2025, M4)",
      "processor": "Apple M4",
      "ram": 24,
      "ssd": 512,
      "min_price": 94050,
      "max_price": 114990,
      "median_price": 102500,
      "buyout_price": 82000,
      "samples_count": 12,
      "updated_at": "Sun Jan 25 22:16:33 2026"
    },
    {
      "model_name": "MacBook Air 15 (2023, M2)",
      "processor": "Apple M2",
      "ram": 8,
      "ssd": 512,
      "min_price": 69148,
      "max_price": 91990,
      "median_price": 80000,
      "buyout_price": 57000,
      "samples_count": 140,
      "updated_at": "Sun Jan 25 22:16:46 2026"
    },
    {
      "model_name": "MacBook Air 15 (2023, M2)",
      "processor": "Apple M2",
      "ram": 8,
      "ssd": 256,
      "min_price": 59990,
      "max_price": 85990,
      "median_price": 68995,
      "buyout_price": 47000,
      "samples_count": 19,
      "updated_at": "Sun Jan 25 18:38:33 2026"
    },
    {
      "model_name": "MacBook Air 15 (2023, M2)",
      "processor": "Apple M2",
      "ram": 16,
      "ssd": 512,
      "min_price": 71990,
      "max_price": 95000,
      "median_price": 81990,
      "buyout_price": 59000,
      "samples_count": 14,
      "updated_at": "Sun Jan 25 22:17:19 2026"
    },
    {
      "model_name": "MacBook Air 15 (2023, M2)",
      "processor": "Apple M2",
      "ram": 16,
      "ssd": 256,
      "min_price": 59990,
      "max_price": 85000,
      "median_price": 65990,
      "buyout_price": 47000,
      "samples_count": 15,
      "updated_at": "Sun Jan 25 03:22:08 2026"
    },
    {
      "model_name": "MacBook Air 15 (2024, M3)",
      "processor": "Apple M3",
      "ram": 8,
      "ssd": 256,
      "min_price": 70000,
      "max_price": 89990,
      "median_price": 79495,
      "buyout_price": 58000,
      "samples_count": 100,
      "updated_at": "Sun Jan 25 22:18:30 2026"
    },
    {
      "model_name": "MacBook Air 15 (2024, M3)",
      "processor": "Apple M3",
      "ram": 8,
      "ssd": 512,
      "min_price": 81500,
      "max_price": 100990,
      "median_price": 94800,
      "buyout_price": 69000,
      "samples_count": 100,
      "updated_at": "Sun Jan 25 22:18:44 2026"
    },
    {
      "model_name": "MacBook Air 15 (2024, M3)",
      "processor": "Apple M3",
      "ram": 16,
      "ssd": 512,
      "min_price": 91990,
      "max_price": 109990,
      "median_price": 102900,
      "buyout_price": 79000,
      "samples_count": 50,
      "updated_at": "Sun Jan 25 22:19:02 2026"
    },
    {
      "model_name": "MacBook Air 15 (2024, M3)",
      "processor": "Apple M3",
      "ram": 16,
      "ssd": 256,
      "min_price": 83500,
      "max_price": 95000,
      "median_price": 86990,
      "buyout_price": 71000,
      "samples_count": 100,
      "updated_at": "Sun Jan 25 22:19:18 2026"
    },
    {
      "model_name": "MacBook Air 15 (2024, M3)",
      "processor": "Apple M3",
      "ram": 24,
      "ssd": 512,
      "min_price": 106000,
      "max_price": 122900,
      "median_price": 114945,
      "buyout_price": 94000,
      "samples_count": 49,
      "updated_at": "Sun Jan 25 22:19:36 2026"
    },
    {
      "model_name": "MacBook Air 15 (2024, M3)",
      "processor": "Apple M3",
      "ram": 16,
      "ssd": 1024,
      "min_price": 109990,
      "max_price": 246990,
      "median_price": 112495,
      "buyout_price": 97000,
      "samples_count": 25,
      "updated_at": "Sun Jan 25 18:41:15 2026"
    },
    {
      "model_name": "MacBook Air 15 (2025, M4)",
      "processor": "Apple M4",
      "ram": 16,
      "ssd": 256,
      "min_price": 86999,
      "max_price": 91000,
      "median_price": 89245,
      "buyout_price": 74000,
      "samples_count": 100,
      "updated_at": "Sun Jan 25 22:19:59 2026"
    },
    {
      "model_name": "MacBook Air 15 (2025, M4)",
      "processor": "Apple M4",
      "ram": 16,
      "ssd": 512,
      "min_price": 105990,
      "max_price": 110990,
      "median_price": 108495,
      "buyout_price": 93000,
      "samples_count": 100,
      "updated_at": "Sun Jan 25 22:20:14 2026"
    },
    {
      "model_name": "MacBook Air 15 (2025, M4)",
      "processor": "Apple M4",
      "ram": 24,
      "ssd": 512,
      "min_price": 105690,
      "max_price": 110990,
      "median_price": 106999,
      "buyout_price": 93000,
      "samples_count": 50,
      "updated_at": "Sun Jan 25 22:20:32 2026"
    },
    {
      "model_name": "MacBook Pro 13 (2020, M1)",
      "processor": "Apple M1",
      "ram": 8,
      "ssd": 256,
      "min_price": 40500,
      "max_price": 50000,
      "median_price": 45000,
      "buyout_price": 28000,
      "samples_count": 95,
      "updated_at": "Sun Jan 25 22:21:05 2026"
    },
    {
      "model_name": "MacBook Pro 13 (2020, M1)",
      "processor": "Apple M1",
      "ram": 8,
      "ssd": 512,
      "min_price": 47990,
      "max_price": 75000,
      "median_price": 60000,
      "buyout_price": 35000,
      "samples_count": 50,
      "updated_at": "Sun Jan 25 22:21:23 2026"
    },
    {
      "model_name": "MacBook Pro 13 (2020, M1)",
      "processor": "Apple M1",
      "ram": 16,
      "ssd": 256,
      "min_price": 46990,
      "max_price": 60000,
      "median_price": 53000,
      "buyout_price": 34000,
      "samples_count": 58,
      "updated_at": "Sun Jan 25 18:43:14 2026"
    },
    {
      "model_name": "MacBook Pro 13 (2020, M1)",
      "processor": "Apple M1",
      "ram": 16,
      "ssd": 1024,
      "min_price": 65000,
      "max_price": 95000,
      "median_price": 75000,
      "buyout_price": 53000,
      "samples_count": 32,
      "updated_at": "Sun Jan 25 22:21:53 2026"
    },
    {
      "model_name": "MacBook Pro 13 (2020, M1)",
      "processor": "Apple M1",
      "ram": 16,
      "ssd": 512,
      "min_price": 50000,
      "max_price": 70000,
      "median_price": 55499,
      "buyout_price": 38000,
      "samples_count": 51,
      "updated_at": "Sun Jan 25 18:44:33 2026"
    },
    {
      "model_name": "MacBook Pro 13 (2022, M2)",
      "processor": "Apple M2",
      "ram": 16,
      "ssd": 256,
      "min_price": 67000,
      "max_price": 111900,
      "median_price": 79990,
      "buyout_price": 55000,
      "samples_count": 18,
      "updated_at": "Sun Jan 25 18:44:47 2026"
    },
    {
      "model_name": "MacBook Pro 13 (2022, M2)",
      "processor": "Apple M2",
      "ram": 8,
      "ssd": 256,
      "min_price": 52000,
      "max_price": 65000,
      "median_price": 59000,
      "buyout_price": 40000,
      "samples_count": 137,
      "updated_at": "Sun Jan 25 22:23:02 2026"
    },
    {
      "model_name": "MacBook Pro 13 (2022, M2)",
      "processor": "Apple M2",
      "ram": 16,
      "ssd": 512,
      "min_price": 105990,
      "max_price": 140000,
      "median_price": 105990,
      "buyout_price": 93000,
      "samples_count": 5,
      "updated_at": "Sun Jan 25 22:23:07 2026"
    },
    {
      "model_name": "MacBook Pro 13 (2022, M2)",
      "processor": "Apple M2",
      "ram": 8,
      "ssd": 512,
      "min_price": 59000,
      "max_price": 79990,
      "median_price": 70000,
      "buyout_price": 47000,
      "samples_count": 78,
      "updated_at": "Sun Jan 25 22:23:21 2026"
    },
    {
      "model_name": "MacBook Pro 14 (2021)",
      "processor": "Apple M1 Pro",
      "ram": 32,
      "ssd": 512,
      "min_price": 75999,
      "max_price": 120990,
      "median_price": 90000,
      "buyout_price": 63000,
      "samples_count": 22,
      "updated_at": "Sun Jan 25 22:23:54 2026"
    },
    {
      "model_name": "MacBook Pro 14 (2021)",
      "processor": "Apple M1 Pro",
      "ram": 16,
      "ssd": 512,
      "min_price": 65000,
      "max_price": 72000,
      "median_price": 69375,
      "buyout_price": 53000,
      "samples_count": 49,
      "updated_at": "Sun Jan 25 22:24:14 2026"
    },
    {
      "model_name": "MacBook Pro 14 (2021)",
      "processor": "Apple M1 Pro",
      "ram": 16,
      "ssd": 1024,
      "min_price": 79000,
      "max_price": 100900,
      "median_price": 85000,
      "buyout_price": 67000,
      "samples_count": 50,
      "updated_at": "Sun Jan 25 22:24:30 2026"
    },
    {
      "model_name": "MacBook Pro 14 (2021)",
      "processor": "Apple M1 Pro",
      "ram": 32,
      "ssd": 1024,
      "min_price": 105000,
      "max_price": 174990,
      "median_price": 174990,
      "buyout_price": 93000,
      "samples_count": 20,
      "updated_at": "Sun Jan 25 18:46:45 2026"
    },
    {
      "model_name": "MacBook Pro 14 (2021)",
      "processor": "Apple M1 Max",
      "ram": 64,
      "ssd": 1024,
      "min_price": 202990,
      "max_price": 202990,
      "median_price": 202990,
      "buyout_price": 190000,
      "samples_count": 6,
      "updated_at": "Sun Jan 25 22:25:24 2026"
    },
    {
      "model_name": "MacBook Pro 14 (2023)",
      "processor": "Apple M2 Pro",
      "ram": 32,
      "ssd": 1024,
      "min_price": 133990,
      "max_price": 180000,
      "median_price": 143990,
      "buyout_price": 121000,
      "samples_count": 18,
      "updated_at": "Sun Jan 25 22:26:57 2026"
    },
    {
      "model_name": "MacBook Pro 14 (2023)",
      "processor": "Apple M3",
      "ram": 16,
      "ssd": 512,
      "min_price": 112990,
      "max_price": 136500,
      "median_price": 128945,
      "buyout_price": 100000,
      "samples_count": 17,
      "updated_at": "Sun Jan 25 22:27:54 2026"
    },
    {
      "model_name": "MacBook Pro 14 (2023)",
      "processor": "Apple M3",
      "ram": 16,
      "ssd": 1024,
      "min_price": 135000,
      "max_price": 171990,
      "median_price": 135990,
      "buyout_price": 123000,
      "samples_count": 5,
      "updated_at": "Sun Jan 25 22:27:37 2026"
    },
    {
      "model_name": "MacBook Pro 14 (2023)",
      "processor": "Apple M3",
      "ram": 8,
      "ssd": 512,
      "min_price": 75000,
      "max_price": 82999,
      "median_price": 79990,
      "buyout_price": 63000,
      "samples_count": 55,
      "updated_at": "Sun Jan 25 22:27:17 2026"
    },
    {
      "model_name": "MacBook Pro 14 (2023)",
      "processor": "Apple M3",
      "ram": 8,
      "ssd": 1024,
      "min_price": 105990,
      "max_price": 134990,
      "median_price": 120990,
      "buyout_price": 93000,
      "samples_count": 85,
      "updated_at": "Sun Jan 25 22:27:31 2026"
    },
    {
      "model_name": "MacBook Pro 14 (2023)",
      "processor": "Apple M3 Max",
      "ram": 36,
      "ssd": 1024,
      "min_price": 193000,
      "max_price": 298900,
      "median_price": 239990,
      "buyout_price": 181000,
      "samples_count": 38,
      "updated_at": "Sun Jan 25 22:28:06 2026"
    },
    {
      "model_name": "MacBook Pro 14 (2023)",
      "processor": "Apple M3 Pro",
      "ram": 18,
      "ssd": 512,
      "min_price": 136800,
      "max_price": 142990,
      "median_price": 139995,
      "buyout_price": 124000,
      "samples_count": 50,
      "updated_at": "Mon Jan 26 07:57:24 2026"
    },
    {
      "model_name": "MacBook Pro 14 (2023)",
      "processor": "Apple M3 Pro",
      "ram": 18,
      "ssd": 1024,
      "min_price": 156990,
      "max_price": 239990,
      "median_price": 191740,
      "buyout_price": 144000,
      "samples_count": 99,
      "updated_at": "Mon Jan 26 07:57:43 2026"
    },
    {
      "model_name": "MacBook Pro 14 (2024)",
      "processor": "Apple M4 Max",
      "ram": 128,
      "ssd": 4096,
      "min_price": 387990,
      "max_price": 610990,
      "median_price": 529990,
      "buyout_price": 375000,
      "samples_count": 44,
      "updated_at": "Mon Jan 26 07:58:27 2026"
    },
    {
      "model_name": "MacBook Pro 14 (2024)",
      "processor": "Apple M4 Pro",
      "ram": 24,
      "ssd": 1024,
      "min_price": 187990,
      "max_price": 206890,
      "median_price": 199990,
      "buyout_price": 175000,
      "samples_count": 141,
      "updated_at": "Sun Jan 25 22:30:28 2026"
    },
    {
      "model_name": "MacBook Pro 14 (2024)",
      "processor": "Apple M4 Pro",
      "ram": 24,
      "ssd": 512,
      "min_price": 154700,
      "max_price": 160000,
      "median_price": 156994,
      "buyout_price": 142000,
      "samples_count": 50,
      "updated_at": "Mon Jan 26 08:00:25 2026"
    },
    {
      "model_name": "MacBook Pro 16 (2021)",
      "processor": "Apple M1 Pro",
      "ram": 16,
      "ssd": 512,
      "min_price": 74990,
      "max_price": 95000,
      "median_price": 81500,
      "buyout_price": 62000,
      "samples_count": 100,
      "updated_at": "Mon Jan 26 08:00:42 2026"
    },
    {
      "model_name": "MacBook Pro 16 (2021)",
      "processor": "Apple M1 Max",
      "ram": 32,
      "ssd": 512,
      "min_price": 95000,
      "max_price": 120000,
      "median_price": 104990,
      "buyout_price": 83000,
      "samples_count": 9,
      "updated_at": "Mon Jan 26 08:02:20 2026"
    },
    {
      "model_name": "MacBook Pro 16 (2021)",
      "processor": "Apple M1 Max",
      "ram": 32,
      "ssd": 1024,
      "min_price": 120000,
      "max_price": 205990,
      "median_price": 143090,
      "buyout_price": 108000,
      "samples_count": 17,
      "updated_at": "Mon Jan 26 08:02:33 2026"
    },
    {
      "model_name": "MacBook Pro 16 (2021)",
      "processor": "Apple M1 Pro",
      "ram": 16,
      "ssd": 1024,
      "min_price": 86000,
      "max_price": 109990,
      "median_price": 98200,
      "buyout_price": 74000,
      "samples_count": 45,
      "updated_at": "Mon Jan 26 08:02:13 2026"
    },
    {
      "model_name": "MacBook Pro 16 (2021)",
      "processor": "Apple M1 Max",
      "ram": 64,
      "ssd": 1024,
      "min_price": 125000,
      "max_price": 214990,
      "median_price": 214990,
      "buyout_price": 113000,
      "samples_count": 9,
      "updated_at": "Mon Jan 26 08:02:44 2026"
    },
    {
      "model_name": "MacBook Pro 16 (2023)",
      "processor": "Apple M2 Pro",
      "ram": 16,
      "ssd": 512,
      "min_price": 115000,
      "max_price": 145990,
      "median_price": 130000,
      "buyout_price": 103000,
      "samples_count": 97,
      "updated_at": "Mon Jan 26 08:03:03 2026"
    },
    {
      "model_name": "MacBook Pro 16 (2023)",
      "processor": "Apple M2 Pro",
      "ram": 16,
      "ssd": 1024,
      "min_price": 140000,
      "max_price": 192990,
      "median_price": 174500,
      "buyout_price": 128000,
      "samples_count": 29,
      "updated_at": "Mon Jan 26 08:03:15 2026"
    },
    {
      "model_name": "MacBook Pro 16 (2023)",
      "processor": "Apple M3 Pro",
      "ram": 18,
      "ssd": 512,
      "min_price": 145000,
      "max_price": 197990,
      "median_price": 181990,
      "buyout_price": 133000,
      "samples_count": 103,
      "updated_at": "Sun Jan 25 22:33:56 2026"
    },
    {
      "model_name": "MacBook Pro 16 (2023)",
      "processor": "Apple M3 Pro",
      "ram": 36,
      "ssd": 512,
      "min_price": 199990,
      "max_price": 249990,
      "median_price": 235995,
      "buyout_price": 187000,
      "samples_count": 49,
      "updated_at": "Mon Jan 26 08:04:17 2026"
    },
    {
      "model_name": "MacBook Pro 16 (2023)",
      "processor": "Apple M3 Max",
      "ram": 48,
      "ssd": 1024,
      "min_price": 279990,
      "max_price": 301990,
      "median_price": 279990,
      "buyout_price": 267000,
      "samples_count": 32,
      "updated_at": "Mon Jan 26 08:04:34 2026"
    },
    {
      "model_name": "MacBook Pro 16 (2023)",
      "processor": "Apple M3 Max",
      "ram": 36,
      "ssd": 1024,
      "min_price": 212990,
      "max_price": 255990,
      "median_price": 240990,
      "buyout_price": 200000,
      "samples_count": 46,
      "updated_at": "Sun Jan 25 22:34:42 2026"
    },
    {
      "model_name": "MacBook Pro 16 (2023)",
      "processor": "Apple M2 Max",
      "ram": 32,
      "ssd": 1024,
      "min_price": 260990,
      "max_price": 339990,
      "median_price": 323990,
      "buyout_price": 248000,
      "samples_count": 8,
      "updated_at": "Sun Jan 25 22:35:00 2026"
    },
    {
      "model_name": "MacBook Pro 16 (2024)",
      "processor": "Apple M4 Max",
      "ram": 36,
      "ssd": 1024,
      "min_price": 269990,
      "max_price": 286990,
      "median_price": 278990,
      "buyout_price": 257000,
      "samples_count": 100,
      "updated_at": "Mon Jan 26 08:06:15 2026"
    },
    {
      "model_name": "MacBook Pro 16 (2024)",
      "processor": "Apple M4 Pro",
      "ram": 48,
      "ssd": 512,
      "min_price": 219990,
      "max_price": 238000,
      "median_price": 229990,
      "buyout_price": 207000,
      "samples_count": 121,
      "updated_at": "Mon Jan 26 08:06:33 2026"
    },
    {
      "model_name": "MacBook Pro 14 (2024)",
      "processor": "Apple M4 Max",
      "ram": 128,
      "ssd": 1024,
      "min_price": 440000,
      "max_price": 556900,
      "median_price": 465000,
      "buyout_price": 428000,
      "samples_count": 10,
      "updated_at": "Mon Jan 26 07:58:09 2026"
    },
    {
      "model_name": "MacBook Pro 14 (2024)",
      "processor": "Apple M4 Max",
      "ram": 128,
      "ssd": 8192,
      "min_price": 630000,
      "max_price": 690900,
      "median_price": 680000,
      "buyout_price": 618000,
      "samples_count": 23,
      "updated_at": "Mon Jan 26 07:58:43 2026"
    },
    {
      "model_name": "MacBook Pro 16 (2023)",
      "processor": "Apple M3 Max",
      "ram": 64,
      "ssd": 1024,
      "min_price": 149990,
      "max_price": 330000,
      "median_price": 199995,
      "buyout_price": 137000,
      "samples_count": 10,
      "updated_at": "Mon Jan 26 08:03:33 2026"
    },
    {
      "model_name": "MacBook Pro 16 (2023)",
      "processor": "Apple M3 Max",
      "ram": 128,
      "ssd": 1024,
      "min_price": 302990,
      "max_price": 509990,
      "median_price": 370000,
      "buyout_price": 290000,
      "samples_count": 26,
      "updated_at": "Mon Jan 26 08:05:43 2026"
    },
    {
      "model_name": "MacBook Pro 16 (2024)",
      "processor": "Apple M4 Max",
      "ram": 48,
      "ssd": 1024,
      "min_price": 319990,
      "max_price": 335990,
      "median_price": 329890,
      "buyout_price": 307000,
      "samples_count": 100,
      "updated_at": "Mon Jan 26 08:06:00 2026"
    },
    {
      "model_name": "MacBook Pro 16 (2024)",
      "processor": "Apple M4 Pro",
      "ram": 24,
      "ssd": 1024,
      "min_price": 235000,
      "max_price": 279900,
      "median_price": 262000,
      "buyout_price": 223000,
      "samples_count": 24,
      "updated_at": "Sun Jan 25 22:36:34 2026"
    },
    {
      "model_name": "MacBook Pro 16 (2024)",
      "processor": "Apple M4 Pro",
      "ram": 24,
      "ssd": 512,
      "min_price": 185000,
      "max_price": 209990,
      "median_price": 198249,
      "buyout_price": 173000,
      "samples_count": 100,
      "updated_at": "Mon Jan 26 08:07:29 2026"
    },
    {
      "model_name": "MacBook Pro 14 (2023)",
      "processor": "Apple M3 Max",
      "ram": 128,
      "ssd": 4096,
      "min_price": 223990,
      "max_price": 293990,
      "median_price": 243990,
      "buyout_price": 211000,
      "samples_count": 14,
      "updated_at": "Sun Jan 25 22:28:19 2026"
    },
    {
      "model_name": "MacBook Air 15 (2025, M4)",
      "processor": "Apple M4",
      "ram": 24,
      "ssd": 1024,
      "min_price": 167990,
      "max_price": 188999,
      "median_price": 179388,
      "buyout_price": 155000,
      "samples_count": 31,
      "updated_at": "Sun Jan 25 18:42:19 2026"
    }
  ]
}